here_map_widget/__init__.py
here_map_widget/_version.py
here_map_widget/configs.py
here_map_widget/map.py
here_map_widget/labextension/package.json
here_map_widget/labextension/static/06398bec2a4a24629c73517760927f57.png
here_map_widget/labextension/static/1eb2198bcb02edfa1389bb2edd400fd8.png
here_map_widget/labextension/static/261.f2970b1f048f38aefd55.js
here_map_widget/labextension/static/271.60993da6b54c8cb97452.js
here_map_widget/labextension/static/349.4b36584e13aa88976f81.js
here_map_widget/labextension/static/349.4b36584e13aa88976f81.js.LICENSE.txt
here_map_widget/labextension/static/378.5f753454cd3e1aae8a48.js
here_map_widget/labextension/static/444.f35562c888b7d2c61b41.js
here_map_widget/labextension/static/486.c31172146691e3dbd7b5.js
here_map_widget/labextension/static/486.c31172146691e3dbd7b5.js.LICENSE.txt
here_map_widget/labextension/static/522.54ebb5dc3d7a2ddb4290.js
here_map_widget/labextension/static/522.54ebb5dc3d7a2ddb4290.js.LICENSE.txt
here_map_widget/labextension/static/536.275ebb84977acc1f998c.js
here_map_widget/labextension/static/536.275ebb84977acc1f998c.js.LICENSE.txt
here_map_widget/labextension/static/549b33bab7247b619c0292995f5a906b.png
here_map_widget/labextension/static/568.109534741052ec9cd039.js
here_map_widget/labextension/static/69fbc9c24b3665b801445c9bccc7017d.png
here_map_widget/labextension/static/f9b7a75b186911a1b04d08f8db305b7a.gif
here_map_widget/labextension/static/remoteEntry.af24992a0ca373a59ee3.js
here_map_widget/labextension/static/style.js
here_map_widget/labextension/static/third-party-licenses.json
here_map_widget/nbextension/06398bec2a4a24629c73517760927f57.png
here_map_widget/nbextension/1eb2198bcb02edfa1389bb2edd400fd8.png
here_map_widget/nbextension/549b33bab7247b619c0292995f5a906b.png
here_map_widget/nbextension/69fbc9c24b3665b801445c9bccc7017d.png
here_map_widget/nbextension/extension.js
here_map_widget/nbextension/f9b7a75b186911a1b04d08f8db305b7a.gif
here_map_widget/nbextension/index.js
here_map_widget_for_jupyter-1.1.3.dist-info/LICENSE
here_map_widget_for_jupyter-1.1.3.dist-info/METADATA
here_map_widget_for_jupyter-1.1.3.dist-info/WHEEL
here_map_widget_for_jupyter-1.1.3.dist-info/top_level.txt
here_map_widget_for_jupyter-1.1.3.dist-info/RECORD
