Metadata-Version: 2.1
Name: here-map-widget-for-jupyter
Version: 1.1.3
Summary: A widget that enables you to use HERE Maps API for JavaScript in Jupyter Notebook.
Home-page: UNKNOWN
Author: HERE Europe B.V.
License: MIT
Keywords: ipython,jupyter,widgets,here-map-widget-for-jupyter
Platform: any
Classifier: Development Status :: 5 - Production/Stable
Classifier: Framework :: IPython
Classifier: Intended Audience :: Developers
Classifier: Intended Audience :: Science/Research
Classifier: Topic :: Software Development :: Libraries
Classifier: License :: OSI Approved :: MIT License
Classifier: Operating System :: OS Independent
Classifier: Programming Language :: Python :: 3
Classifier: Programming Language :: Python :: 3 :: Only
Classifier: Programming Language :: Python :: 3.7
Classifier: Programming Language :: Python :: 3.8
Classifier: Programming Language :: Python :: 3.9
License-File: LICENSE
Requires-Dist: ipywidgets (<8,>=7.6.0)
Requires-Dist: branca (<0.5,>=0.3.1)
Requires-Dist: xyzservices (>=2021.8.0)
Provides-Extra: dev
Requires-Dist: black[jupyter] ; extra == 'dev'
Requires-Dist: isort ; extra == 'dev'
